{
  "db_name": "PostgreSQL",
  "query": "\n        SELECT b.*\n        FROM blobs b\n        JOIN transactions t ON b.tx_hash = t.tx_hash\n        WHERE b.contract_name = $1 AND t.transaction_status = 'Success'\n        ",
  "describe": {
    "columns": [
      {
        "ordinal": 0,
        "name": "tx_hash",
        "type_info": "Bytea"
      },
      {
        "ordinal": 1,
        "name": "blob_index",
        "type_info": "Int4"
      },
      {
        "ordinal": 2,
        "name": "identity",
        "type_info": "Text"
      },
      {
        "ordinal": 3,
        "name": "contract_name",
        "type_info": "Text"
      },
      {
        "ordinal": 4,
        "name": "data",
        "type_info": "Bytea"
      }
    ],
    "parameters": {
      "Left": [
        "Text"
      ]
    },
    "nullable": [
      false,
      false,
      false,
      false,
      false
    ]
  },
  "hash": "62c7405e1fc4387a56f829454d3ee031b0f02f4f2118f584738c21592c6ed94f"
}
