{
  "db_name": "PostgreSQL",
  "query": "INSERT INTO transactions (tx_hash, block_hash, tx_index, version, transaction_type, transaction_status)\n                        VALUES ($1, $2, $3, $4, $5, $6)",
  "describe": {
    "columns": [],
    "parameters": {
      "Left": [
        "Bytea",
        "Bytea",
        "Int4",
        "Int4",
        {
          "Custom": {
            "name": "transaction_type",
            "kind": {
              "Enum": [
                "BlobTransaction",
                "ProofTransaction",
                "RegisterContractTransaction"
              ]
            }
          }
        },
        {
          "Custom": {
            "name": "transaction_status",
            "kind": {
              "Enum": [
                "Success",
                "Failure",
                "Sequenced"
              ]
            }
          }
        }
      ]
    },
    "nullable": []
  },
  "hash": "5f9078c356415a8920728f398a5e55aebc8303bca035fea918943865655d30a5"
}
